daytona_daemon_api_client/__init__.py
daytona_daemon_api_client/api_client.py
daytona_daemon_api_client/api_response.py
daytona_daemon_api_client/configuration.py
daytona_daemon_api_client/exceptions.py
daytona_daemon_api_client/py.typed
daytona_daemon_api_client/rest.py
daytona_daemon_api_client/api/__init__.py
daytona_daemon_api_client/api/computer_use_api.py
daytona_daemon_api_client/api/file_system_api.py
daytona_daemon_api_client/api/git_api.py
daytona_daemon_api_client/api/info_api.py
daytona_daemon_api_client/api/lsp_api.py
daytona_daemon_api_client/api/port_api.py
daytona_daemon_api_client/api/process_api.py
daytona_daemon_api_client/models/__init__.py
daytona_daemon_api_client/models/command.py
daytona_daemon_api_client/models/completion_context.py
daytona_daemon_api_client/models/completion_item.py
daytona_daemon_api_client/models/completion_list.py
daytona_daemon_api_client/models/computer_use_start_response.py
daytona_daemon_api_client/models/computer_use_status_response.py
daytona_daemon_api_client/models/computer_use_stop_response.py
daytona_daemon_api_client/models/create_session_request.py
daytona_daemon_api_client/models/display_info.py
daytona_daemon_api_client/models/display_info_response.py
daytona_daemon_api_client/models/execute_request.py
daytona_daemon_api_client/models/execute_response.py
daytona_daemon_api_client/models/file_info.py
daytona_daemon_api_client/models/file_status.py
daytona_daemon_api_client/models/git_add_request.py
daytona_daemon_api_client/models/git_branch_request.py
daytona_daemon_api_client/models/git_checkout_request.py
daytona_daemon_api_client/models/git_clone_request.py
daytona_daemon_api_client/models/git_commit_info.py
daytona_daemon_api_client/models/git_commit_request.py
daytona_daemon_api_client/models/git_commit_response.py
daytona_daemon_api_client/models/git_git_delete_branch_request.py
daytona_daemon_api_client/models/git_repo_request.py
daytona_daemon_api_client/models/git_status.py
daytona_daemon_api_client-0.102.0rc1.dist-info/licenses/LICENSE
daytona_daemon_api_client-0.102.0rc1.dist-info/METADATA
daytona_daemon_api_client-0.102.0rc1.dist-info/WHEEL
daytona_daemon_api_client-0.102.0rc1.dist-info/top_level.txt
daytona_daemon_api_client-0.102.0rc1.dist-info/RECORD
